inputdev.py
setup.py
inputdev.egg-info/PKG-INFO
inputdev.egg-info/SOURCES.txt
inputdev.egg-info/dependency_links.txt
inputdev.egg-info/top_level.txt