Metadata-Version: 1.0
Name: inputdev
Version: 0.0.1421587592
Summary: A library for identifying and directly reading input devices
Home-page: UNKNOWN
Author: Mike Lang
Author-email: mikelang3000@gmail.com
License: UNKNOWN
Platform: UNKNOWN
